pyConfigAnalysis/ConfigAnalysis.py
pyConfigAnalysis/__init__.py
pyConfigAnalysis-1.0.4.dist-info/DESCRIPTION.rst
pyConfigAnalysis-1.0.4.dist-info/METADATA
pyConfigAnalysis-1.0.4.dist-info/RECORD
pyConfigAnalysis-1.0.4.dist-info/WHEEL
pyConfigAnalysis-1.0.4.dist-info/metadata.json
pyConfigAnalysis-1.0.4.dist-info/top_level.txt
